utg900e/__init__.py
utg900e/utg900e.py
utg900e-0.1.0.dist-info/licenses/LICENSE
utg900e-0.1.0.dist-info/METADATA
utg900e-0.1.0.dist-info/WHEEL
utg900e-0.1.0.dist-info/top_level.txt
utg900e-0.1.0.dist-info/RECORD
